<?xml version="1.0" encoding="UTF-8"?>
<!DOCTYPE mapper PUBLIC "-//mybatis.org//DTD Mapper 3.0//EN" "http://mybatis.org/dtd/mybatis-3-mapper.dtd">
<mapper namespace="com.example.torder.mapper.RoleMapper">
  <resultMap id="BaseResultMap" type="com.example.torder.domain.Role">
    <!--
      WARNING - @mbg.generated
      This element is automatically generated by MyBatis Generator, do not modify.
    -->
    <id column="role_id" jdbcType="INTEGER" property="roleId" />
    <result column="role_name" jdbcType="VARCHAR" property="roleName" />
    <result column="role_des" jdbcType="VARCHAR" property="roleDes" />
    <result column="role_parent_id" jdbcType="INTEGER" property="roleParentId" />
    <result column="opr" jdbcType="VARCHAR" property="opr" />
    <result column="oprtime" jdbcType="TIMESTAMP" property="oprtime" />
  </resultMap>
  <sql id="Base_Column_List">
    <!--
      WARNING - @mbg.generated
      This element is automatically generated by MyBatis Generator, do not modify.
    -->
    role_id, role_name, role_des, role_parent_id, opr, oprtime
  </sql>
  <select id="selectByPrimaryKey" parameterType="java.lang.Integer" resultMap="BaseResultMap">
    <!--
      WARNING - @mbg.generated
      This element is automatically generated by MyBatis Generator, do not modify.
    -->
    select 
    <include refid="Base_Column_List" />
    from role_info
    where role_id = #{roleId,jdbcType=INTEGER}
  </select>
  <delete id="deleteByPrimaryKey" parameterType="java.lang.Integer">
    <!--
      WARNING - @mbg.generated
      This element is automatically generated by MyBatis Generator, do not modify.
    -->
    delete from role_info
    where role_id = #{roleId,jdbcType=INTEGER}
  </delete>
  <insert id="insert" parameterType="com.example.torder.domain.Role">
    <!--
      WARNING - @mbg.generated
      This element is automatically generated by MyBatis Generator, do not modify.
    -->
    insert into role_info (role_id, role_name, role_des, 
      role_parent_id, opr, oprtime
      )
    values (#{roleId,jdbcType=INTEGER}, #{roleName,jdbcType=VARCHAR}, #{roleDes,jdbcType=VARCHAR}, 
      #{roleParentId,jdbcType=INTEGER}, #{opr,jdbcType=VARCHAR}, #{oprtime,jdbcType=TIMESTAMP}
      )
  </insert>
  <insert id="insertSelective" parameterType="com.example.torder.domain.Role">
    <!--
      WARNING - @mbg.generated
      This element is automatically generated by MyBatis Generator, do not modify.
    -->
    insert into role_info
    <trim prefix="(" suffix=")" suffixOverrides=",">
      <if test="roleId != null">
        role_id,
      </if>
      <if test="roleName != null">
        role_name,
      </if>
      <if test="roleDes != null">
        role_des,
      </if>
      <if test="roleParentId != null">
        role_parent_id,
      </if>
      <if test="opr != null">
        opr,
      </if>
      <if test="oprtime != null">
        oprtime,
      </if>
    </trim>
    <trim prefix="values (" suffix=")" suffixOverrides=",">
      <if test="roleId != null">
        #{roleId,jdbcType=INTEGER},
      </if>
      <if test="roleName != null">
        #{roleName,jdbcType=VARCHAR},
      </if>
      <if test="roleDes != null">
        #{roleDes,jdbcType=VARCHAR},
      </if>
      <if test="roleParentId != null">
        #{roleParentId,jdbcType=INTEGER},
      </if>
      <if test="opr != null">
        #{opr,jdbcType=VARCHAR},
      </if>
      <if test="oprtime != null">
        #{oprtime,jdbcType=TIMESTAMP},
      </if>
    </trim>
  </insert>
  <update id="updateByPrimaryKeySelective" parameterType="com.example.torder.domain.Role">
    <!--
      WARNING - @mbg.generated
      This element is automatically generated by MyBatis Generator, do not modify.
    -->
    update role_info
    <set>
      <if test="roleName != null">
        role_name = #{roleName,jdbcType=VARCHAR},
      </if>
      <if test="roleDes != null">
        role_des = #{roleDes,jdbcType=VARCHAR},
      </if>
      <if test="roleParentId != null">
        role_parent_id = #{roleParentId,jdbcType=INTEGER},
      </if>
      <if test="opr != null">
        opr = #{opr,jdbcType=VARCHAR},
      </if>
      <if test="oprtime != null">
        oprtime = #{oprtime,jdbcType=TIMESTAMP},
      </if>
    </set>
    where role_id = #{roleId,jdbcType=INTEGER}
  </update>
  <update id="updateByPrimaryKey" parameterType="com.example.torder.domain.Role">
    <!--
      WARNING - @mbg.generated
      This element is automatically generated by MyBatis Generator, do not modify.
    -->
    update role_info
    set role_name = #{roleName,jdbcType=VARCHAR},
      role_des = #{roleDes,jdbcType=VARCHAR},
      role_parent_id = #{roleParentId,jdbcType=INTEGER},
      opr = #{opr,jdbcType=VARCHAR},
      oprtime = #{oprtime,jdbcType=TIMESTAMP}
    where role_id = #{roleId,jdbcType=INTEGER}
  </update>
</mapper>